{"lTransactionResult":[{"transactionID":"PRE_Localization_gpu_POST","timeUnit":"ps","schedulerParentTransactionID":"","releaseParentTransactionID":"","lPhase":["Localization_Preprocessing","Localization","Localization_Postprocessing"],"delayUpperBound":-1.0,"delayLowerBound":-1.0,"deadlineMissed":true},{"transactionID":"PRE_Lane_detection_gpu_POST","timeUnit":"ps","schedulerParentTransactionID":"","releaseParentTransactionID":"","lPhase":["Lane_Detection_Preprocessing","Lane_detection","Lane_Detection_Postprocessing"],"delayUpperBound":-1.0,"delayLowerBound":-1.0,"deadlineMissed":true},{"transactionID":"PRE_Detection_gpu_POST","timeUnit":"ps","schedulerParentTransactionID":"","releaseParentTransactionID":"","lPhase":["Detection_Preprocessing","Detection","Detection_Postprocessing"],"delayUpperBound":-1.0,"delayLowerBound":-1.0,"deadlineMissed":true},{"transactionID":"PRE_SFM_gpu_POST","timeUnit":"ps","schedulerParentTransactionID":"","releaseParentTransactionID":"","lPhase":["SFM_Preprocessing","SFM","SFM_Postprocessing"],"delayUpperBound":-1.0,"delayLowerBound":-1.0,"deadlineMissed":true}],"lExecutableResult":[{"executableID":"Localization_Preprocessing","timeUnit":"ps","schedulerParentExecutableID":"","releaseParentExecutableID":"PRE_Localization_gpu_POST","delayUpperBound":10000748,"delayLowerBound":3393508,"executionUpperBound":8218244.0,"executionLowerBound":3018244.0,"executionAverage":5618244.0,"deadlineMissed":false},{"executableID":"Localization","timeUnit":"ps","schedulerParentExecutableID":"","releaseParentExecutableID":"PRE_Localization_gpu_POST","delayUpperBound":-1,"delayLowerBound":-1,"executionUpperBound":1.23999999E8,"executionLowerBound":1.16999999E8,"executionAverage":1.20499999E8,"deadlineMissed":true},{"executableID":"Localization_Postprocessing","timeUnit":"ps","schedulerParentExecutableID":"","releaseParentExecutableID":"PRE_Localization_gpu_POST","delayUpperBound":126838164,"delayLowerBound":123635284,"executionUpperBound":6299997.0,"executionLowerBound":3099997.0,"executionAverage":4699997.0,"deadlineMissed":false},{"executableID":"DASM","timeUnit":"ps","schedulerParentExecutableID":"","releaseParentExecutableID":"DASM","delayUpperBound":1874075,"delayLowerBound":1301275,"executionUpperBound":1859995.0,"executionLowerBound":1299995.0,"executionAverage":1579995.0,"deadlineMissed":false},{"executableID":"Planner","timeUnit":"ps","schedulerParentExecutableID":"","releaseParentExecutableID":"Planner","delayUpperBound":-1,"delayLowerBound":-1,"executionUpperBound":1.3241911E7,"executionLowerBound":9621911.0,"executionAverage":1.1431911E7,"deadlineMissed":true},{"executableID":"Lane_Detection_Preprocessing","timeUnit":"ps","schedulerParentExecutableID":"","releaseParentExecutableID":"PRE_Lane_detection_gpu_POST","delayUpperBound":-1,"delayLowerBound":-1,"executionUpperBound":3978460.0,"executionLowerBound":3289205.0,"executionAverage":3633832.0,"deadlineMissed":true},{"executableID":"Lane_detection","timeUnit":"ps","schedulerParentExecutableID":"","releaseParentExecutableID":"PRE_Lane_detection_gpu_POST","delayUpperBound":-1,"delayLowerBound":-1,"executionUpperBound":2.7333333E7,"executionLowerBound":2.4499999E7,"executionAverage":2.5916666E7,"deadlineMissed":true},{"executableID":"Lane_Detection_Postprocessing","timeUnit":"ps","schedulerParentExecutableID":"","releaseParentExecutableID":"PRE_Lane_detection_gpu_POST","delayUpperBound":-1,"delayLowerBound":-1,"executionUpperBound":4256840.0,"executionLowerBound":3499642.0,"executionAverage":3878241.0,"deadlineMissed":true},{"executableID":"Detection_Preprocessing","timeUnit":"ps","schedulerParentExecutableID":"","releaseParentExecutableID":"PRE_Detection_gpu_POST","delayUpperBound":-1,"delayLowerBound":-1,"executionUpperBound":3692060.0,"executionLowerBound":3191780.0,"executionAverage":3441920.0,"deadlineMissed":true},{"executableID":"Detection","timeUnit":"ps","schedulerParentExecutableID":"","releaseParentExecutableID":"PRE_Detection_gpu_POST","delayUpperBound":-1,"delayLowerBound":-1,"executionUpperBound":1.15999999E8,"executionLowerBound":1.07999999E8,"executionAverage":1.11999999E8,"deadlineMissed":true},{"executableID":"Detection_Postprocessing","timeUnit":"ps","schedulerParentExecutableID":"","releaseParentExecutableID":"PRE_Detection_gpu_POST","delayUpperBound":-1,"delayLowerBound":-1,"executionUpperBound":1020000.0,"executionLowerBound":820000.0,"executionAverage":920000.0,"deadlineMissed":true},{"executableID":"OS_Overhead","timeUnit":"ps","schedulerParentExecutableID":"","releaseParentExecutableID":"OS_Overhead","delayUpperBound":50000000,"delayLowerBound":50000000,"executionUpperBound":5.0E7,"executionLowerBound":5.0E7,"executionAverage":5.0E7,"deadlineMissed":false},{"executableID":"EKF","timeUnit":"ps","schedulerParentExecutableID":"","releaseParentExecutableID":"EKF","delayUpperBound":5394550,"delayLowerBound":3982550,"executionUpperBound":4759670.0,"executionLowerBound":3979670.0,"executionAverage":4369670.0,"deadlineMissed":false},{"executableID":"CANbus_polling","timeUnit":"ps","schedulerParentExecutableID":"","releaseParentExecutableID":"CANbus_polling","delayUpperBound":603200,"delayLowerBound":400000,"executionUpperBound":599680.0,"executionLowerBound":399680.0,"executionAverage":499680.0,"deadlineMissed":false},{"executableID":"Lidar_Grabber","timeUnit":"ps","schedulerParentExecutableID":"","releaseParentExecutableID":"Lidar_Grabber","delayUpperBound":12946182,"delayLowerBound":10231512,"executionUpperBound":1.0868E7,"executionLowerBound":9794000.0,"executionAverage":1.0331E7,"deadlineMissed":false},{"executableID":"SFM_Preprocessing","timeUnit":"ps","schedulerParentExecutableID":"","releaseParentExecutableID":"PRE_SFM_gpu_POST","delayUpperBound":5555147,"delayLowerBound":3078228,"executionUpperBound":3180071.0,"executionLowerBound":2578212.0,"executionAverage":2879141.0,"deadlineMissed":false},{"executableID":"SFM","timeUnit":"ps","schedulerParentExecutableID":"","releaseParentExecutableID":"PRE_SFM_gpu_POST","delayUpperBound":-1,"delayLowerBound":-1,"executionUpperBound":7899999.0,"executionLowerBound":7049999.0,"executionAverage":7474999.0,"deadlineMissed":true},{"executableID":"SFM_Postprocessing","timeUnit":"ps","schedulerParentExecutableID":"","releaseParentExecutableID":"PRE_SFM_gpu_POST","delayUpperBound":15052103,"delayLowerBound":13405819,"executionUpperBound":3532258.0,"executionLowerBound":2834784.0,"executionAverage":3183521.0,"deadlineMissed":false}],"lEventChainResult":[{"eventChainID":"EC_LidarGrabber_to_DASM","timeUnit":"ps","tasks":["Lidar_Grabber","PRE_Localization_gpu_POST","EKF","Planner","DASM"],"endToEndLatencyImplicit":2.00438874075E11,"endToEndLatencyLET":8.75E8},{"eventChainID":"EC_CAN_DASM","timeUnit":"ps","tasks":["CANbus_polling","PRE_Localization_gpu_POST","EKF","Planner","DASM"],"endToEndLatencyImplicit":2.00426874075E11,"endToEndLatencyLET":8.45E8},{"eventChainID":"EC_SFM_DASM","timeUnit":"ps","tasks":["PRE_SFM_gpu_POST","Planner","DASM"],"endToEndLatencyImplicit":2.00015874075E11,"endToEndLatencyLET":6.5E7},{"eventChainID":"EC_LaneDetection_DASM","timeUnit":"ps","tasks":["PRE_Lane_detection_gpu_POST","Planner","DASM"],"endToEndLatencyImplicit":1.00013874075E11,"endToEndLatencyLET":9.8E7},{"eventChainID":"EC_Detection_DASM","timeUnit":"ps","tasks":["PRE_Detection_gpu_POST","Planner","DASM"],"endToEndLatencyImplicit":1.00011874075E11,"endToEndLatencyLET":2.3E8}]}